valuation/__init__.py
valuation/exceptions.py
valuation/global_settings.py
valuation/helper_interface.py
valuation/run_valuation.py
valuation/sitecustomize.py
valuation/consts/__init__.py
valuation/consts/fields.py
valuation/consts/global_parameters.py
valuation/consts/pl.py
valuation/consts/result.py
valuation/consts/signatures.py
valuation/consts/types.py
valuation/daa_utils_package/__init__.py
valuation/daa_utils_package/daa_utils-1.0.3-py3-none-any.whl
valuation/engine/__init__.py
valuation/engine/base_object.py
valuation/engine/check.py
valuation/engine/data_base.py
valuation/engine/defaults.py
valuation/engine/documentation.py
valuation/engine/exceptions.py
valuation/engine/factory.py
valuation/engine/mappings.py
valuation/engine/utils.py
valuation/engine/calendar_loader/__init__.py
valuation/engine/calendar_loader/loader.py
valuation/engine/calendar_loader/data/ANGLO_AMERICAN.csv
valuation/engine/calendar_loader/data/ARGENTINA.csv
valuation/engine/calendar_loader/data/AUSTRALIA.csv
valuation/engine/calendar_loader/data/AUSTRIA.csv
valuation/engine/calendar_loader/data/BELGIUM.csv
valuation/engine/calendar_loader/data/BRAZIL.csv
valuation/engine/calendar_loader/data/CANADA.csv
valuation/engine/calendar_loader/data/CHILE.csv
valuation/engine/calendar_loader/data/COLOMBIA.csv
valuation/engine/calendar_loader/data/COTE_D`IVOIRE.csv
valuation/engine/calendar_loader/data/CROATIA.csv
valuation/engine/calendar_loader/data/CYPRUS.csv
valuation/engine/calendar_loader/data/CZECH_REPUBLIC.csv
valuation/engine/calendar_loader/data/DENMARK.csv
valuation/engine/calendar_loader/data/ESTONIA.csv
valuation/engine/calendar_loader/data/EUROCLEAR.csv
valuation/engine/calendar_loader/data/FINLAND.csv
valuation/engine/calendar_loader/data/FRANCE.csv
valuation/engine/calendar_loader/data/GERMANY.csv
valuation/engine/calendar_loader/data/GREAT_BRITAIN.csv
valuation/engine/calendar_loader/data/GREECE.csv
valuation/engine/calendar_loader/data/GUERNSEY.csv
valuation-0.1.8.dist-info/LICENSE
valuation-0.1.8.dist-info/METADATA
valuation-0.1.8.dist-info/WHEEL
valuation-0.1.8.dist-info/top_level.txt
valuation-0.1.8.dist-info/RECORD
