Metadata-Version: 2.1
Name: valuation
Version: 0.1.8
Summary: Financial Valuation Engine
Home-page: https://github.com/Deloitte-Audit-Analytics/DaaValuationEngine
Author: Deloitte Audit Analytics GmbH | Valuation
Author-email: daa-valuation@deloitte-audit-analytics.com
Project-URL: Bug Tracker, https://scdm-financial.atlassian.net/jira/software/projects/OP/boards/48/backlog
Classifier: Programming Language :: Python :: 3
Classifier: Operating System :: OS Independent
Requires-Python: >=3.9
License-File: LICENSE
